aprendo/__init__.py
aprendo/quiz.py
aprendo/abstract/__init__.py
aprendo/abstract/word.py
aprendo/db/__init__.py
aprendo/db/base_db.py
aprendo/db/nouns_db.py
aprendo/db/regular_verbs_db.py
aprendo/nouns/__init__.py
aprendo/nouns/noun.py
aprendo/verbs/__init__.py
aprendo/verbs/ar_regular_verb.py
aprendo/verbs/constants.py
aprendo/verbs/er_regular_verb.py
aprendo/verbs/ir_regular_verb.py
aprendo/verbs/regular_verb.py
aprendo/verbs/verb.py
aprendo-0.0.1.dist-info/LICENSE
aprendo-0.0.1.dist-info/METADATA
aprendo-0.0.1.dist-info/WHEEL
aprendo-0.0.1.dist-info/top_level.txt
aprendo-0.0.1.dist-info/RECORD
