Metadata-Version: 2.1
Name: aprendo
Version: 0.0.1
Summary: Quieres aprender español? "Aprendo" es la solución! Add, edit, conjugate, learn and test your Spanish verbs and vocab.
Home-page: https://github.com/luiHoll97/aprendo
Author: Lui Holliday
Author-email: tech.luiholl@gmail.com
License-File: LICENSE
Requires-Dist: questionary
